{
  "code": 200,
  "message": "获取成功",
  "data": [
    [{
      "id":0,
      "title":"面对面红包",
      "icon":"/static/img/purse2.png"
    },{
      "id":1,
      "title":"手机充值",
      "icon":"/static/img/purse5.png"
    },{
      "id":2,
      "title":"理财通",
      "icon":"/static/img/purse1.png"
    },{
      "id":3,
      "title":"Q币充值",
      "icon":"/static/img/purse6.png"
    },{
      "id":4,
      "title":"生活缴费",
      "icon":"/static/img/purse7.png"
    },{
      "id":5,
      "title":"城市服务",
      "icon":"/static/img/purse8.png"
    },{
      "id":6,
      "title":"信用卡还款",
      "icon":"/static/img/purse4.png"
    },{
      "id":7,
      "title":"腾讯公益",
      "icon":"/static/img/purse10.png"
    }],
    [{
      "id":0,
      "title":"滴滴出行",
      "icon":"/static/img/purse11.png"
    },{
      "id":1,
      "title":"火车票机票",
      "icon":"/static/img/purse12.png"
    },{
      "id":2,
      "title":"酒店",
      "icon":"/static/img/purse3.png"
    },{
      "id":3,
      "title":"美团外卖",
      "icon":"/static/img/purse13.png"
    },{
      "id":4,
      "title":"58到家",
      "icon":"/static/img/purse14.png"
    },{
      "id":5,
      "title":"美丽说",
      "icon":"/static/img/purse15.png"
    },{
      "id":6,
      "title":"京东优选",
      "icon":"/static/img/purse16.png"
    },{
      "id":7,
      "title":"电影演出赛事",
      "icon":"/static/img/purse18.png"
    },{
      "id":8,
      "title":"吃喝玩乐",
      "icon":"/static/img/purse19.png"
    }]
  ]
}